huatool/__init__.py
huatool/container.py
huatool/detector.py
huatool/parser.py
huatool/proxy.py
hua_tool-0.1.7.dist-info/LICENSE
hua_tool-0.1.7.dist-info/METADATA
hua_tool-0.1.7.dist-info/WHEEL
hua_tool-0.1.7.dist-info/top_level.txt
hua_tool-0.1.7.dist-info/RECORD
