Metadata-Version: 2.1
Name: hua-tool
Version: 0.1.7
Summary: Hua777 專用的 Python 工具
Home-page: https://github.com/Hua777
Author: Hua777
Author-email: liao.700529@gmail.com
License: MIT License
Keywords: hua tool
Platform: any
Requires-Dist: python-dateutil
Requires-Dist: beautifulsoup4
Requires-Dist: requests
